sapi/__init__.py
sapi/exceptions.py
sapi/normal.py
sapi/utility.py
sapi/wsgi.py
sapi/app/__init__.py
sapi/app/api.py
sapi/app/main.py
sapi/config/__init__.py
sapi/config/ca.py
sapi/config/general.py
sapi/config/log.py
sapi/config/server.py
sapi/config/urls.py
sapi/config/api/__init__.py
sapi/config/api/server.py
sapi/config/api/signing_hooks_base.py
sapi/config/api/urls.py
sapi/resources/gunicorn.conf.dev
sapi/resources/gunicorn.conf.prod
sapi/resources/README.rst
sapi/resources/requirements.txt
sapi/resources/data/gunicorn.conf.dev
sapi/resources/data/gunicorn.conf.prod
sapi/resources/scripts/ca_create_identity
sapi/resources/scripts/ca_sign_certificate
sapi/resources/scripts/ca_sign_subordinate
sapi/resources/scripts/ca_start_dev
sapi/resources/scripts/ca_start_gunicorn_dev
sapi/resources/scripts/ca_start_gunicorn_prod
sapi/script_logic/__init__.py
sapi/script_logic/ca_create_identity.py
sapi/script_logic/ca_sign_certificate.py
sapi/script_logic/ca_sign_subordinate.py
sapi/script_logic/start_dev.py
sapi/ssl/__init__.py
sapi/ssl/ca.py
sapi/ssl/certs.py
sapi/ssl/helper.py
sapi/ssl/keys.py
sapi/ssl/requests.py
sapi/ssl/utility.py
sapi/views/__init__.py
sapi/views/index.py
sapi/views/ping.py
sapi/views/api/__init__.py
sapi/views/api/csr.py
scripts/__init__.py
scripts/ca_create_identity
scripts/ca_sign_subordinate
scripts/ca_start_dev
scripts/ca_start_gunicorn_dev
scripts/ca_start_gunicorn_prod
ssl_api-0.2.33.data/scripts/ca_create_identity
ssl_api-0.2.33.data/scripts/ca_sign_certificate
ssl_api-0.2.33.data/scripts/ca_sign_subordinate
ssl_api-0.2.33.data/scripts/ca_start_dev
ssl_api-0.2.33.data/scripts/ca_start_gunicorn_dev
ssl_api-0.2.33.data/scripts/ca_start_gunicorn_prod
ssl_api-0.2.33.dist-info/DESCRIPTION.rst
ssl_api-0.2.33.dist-info/METADATA
ssl_api-0.2.33.dist-info/metadata.json
ssl_api-0.2.33.dist-info/RECORD
ssl_api-0.2.33.dist-info/top_level.txt
ssl_api-0.2.33.dist-info/WHEEL
