Metadata-Version: 2.0
Name: ssl-api
Version: 0.2.33
Summary: A certificate-authority API.
Home-page: https://github.com/dsoprea/SslApi
Author: Dustin Oprea
Author-email: myselfasunder@gmail.com
License: GPL 2
Keywords: ssl openssl ca certificate authority api
Platform: UNKNOWN
Requires-Dist: Jinja2 (==2.7.2)
Requires-Dist: M2Crypto (==0.22.3)
Requires-Dist: MarkupSafe (==0.21)
Requires-Dist: cffi (==0.8.2)
Requires-Dist: cryptography (==0.4)
Requires-Dist: gunicorn (==19.1.0)
Requires-Dist: pyOpenSSL (==0.14)
Requires-Dist: pyasn1 (==0.1.7)
Requires-Dist: pyasn1-modules (==0.0.5)
Requires-Dist: pycparser (==2.10)
Requires-Dist: six (==1.6.1)
Requires-Dist: web.py (==0.37)
Requires-Dist: wsgiref (==0.1.2)
